<DOMSymbolItem xmlns="http://ns.adobe.com/xfl/2008/" xmlns:xsi="http://www.w3.org/2001/XMLSchema-instance" name="Symbol 273" itemID="69d5d180-000000b0" lastModified="1775619668">
     <timeline>
          <DOMTimeline name="Symbol 273">
               <layers>
                    <DOMLayer name="Layer 1" color="#3fe8ee">
                         <frames>
                              <DOMFrame index="0" keyMode="9728">
                                   <elements>
                                        <DOMSymbolInstance libraryItemName="Symbol 149" centerPoint3DX="-7.5" centerPoint3DY="6.5">
                                             <matrix>
                                                  <Matrix tx="-14.0" ty="0.0" a="0.0" d="0.0" b="1.0" c="-1.0"/>
                                             </matrix>
                                             <transformationPoint>
                                                  <Point/>
                                             </transformationPoint>
                                        </DOMSymbolInstance>
                                   </elements>
                              </DOMFrame>
                         </frames>
                    </DOMLayer>
                    <DOMLayer name="Layer 2" color="#e3a7e2">
                         <frames>
                              <DOMFrame index="0" keyMode="9728">
                                   <elements>
                                        <DOMSymbolInstance libraryItemName="Symbol 149" centerPoint3DX="-21.5" centerPoint3DY="6.5">
                                             <matrix>
                                                  <Matrix tx="-28.0" ty="0.0" a="0.0" d="0.0" b="1.0" c="-1.0"/>
                                             </matrix>
                                             <transformationPoint>
                                                  <Point/>
                                             </transformationPoint>
                                        </DOMSymbolInstance>
                                   </elements>
                              </DOMFrame>
                         </frames>
                    </DOMLayer>
                    <DOMLayer name="Layer 3" color="#62efda">
                         <frames>
                              <DOMFrame index="0" keyMode="9728">
                                   <elements>
                                        <DOMSymbolInstance libraryItemName="Symbol 149" centerPoint3DX="34.5" centerPoint3DY="6.5">
                                             <matrix>
                                                  <Matrix tx="28.0" ty="0.0" a="0.0" d="0.0" b="1.0" c="-1.0"/>
                                             </matrix>
                                             <transformationPoint>
                                                  <Point/>
                                             </transformationPoint>
                                        </DOMSymbolInstance>
                                   </elements>
                              </DOMFrame>
                         </frames>
                    </DOMLayer>
                    <DOMLayer name="Layer 4" color="#76c6b5">
                         <frames>
                              <DOMFrame index="0" keyMode="9728">
                                   <elements>
                                        <DOMSymbolInstance libraryItemName="Symbol 149" centerPoint3DX="20.5" centerPoint3DY="6.5">
                                             <matrix>
                                                  <Matrix tx="14.0" ty="0.0" a="0.0" d="0.0" b="1.0" c="-1.0"/>
                                             </matrix>
                                             <transformationPoint>
                                                  <Point/>
                                             </transformationPoint>
                                        </DOMSymbolInstance>
                                   </elements>
                              </DOMFrame>
                         </frames>
                    </DOMLayer>
                    <DOMLayer name="Layer 5" color="#d030d4">
                         <frames>
                              <DOMFrame index="0" keyMode="9728">
                                   <elements>
                                        <DOMSymbolInstance libraryItemName="Symbol 149" centerPoint3DX="6.5" centerPoint3DY="20.5">
                                             <matrix>
                                                  <Matrix tx="0.0" ty="14.0"/>
                                             </matrix>
                                             <transformationPoint>
                                                  <Point/>
                                             </transformationPoint>
                                        </DOMSymbolInstance>
                                   </elements>
                              </DOMFrame>
                         </frames>
                    </DOMLayer>
                    <DOMLayer name="Layer 6" color="#70fe55">
                         <frames>
                              <DOMFrame index="0" keyMode="9728">
                                   <elements>
                                        <DOMSymbolInstance libraryItemName="Symbol 149" centerPoint3DX="6.5" centerPoint3DY="34.5">
                                             <matrix>
                                                  <Matrix tx="0.0" ty="28.0"/>
                                             </matrix>
                                             <transformationPoint>
                                                  <Point/>
                                             </transformationPoint>
                                        </DOMSymbolInstance>
                                   </elements>
                              </DOMFrame>
                         </frames>
                    </DOMLayer>
                    <DOMLayer name="Layer 7" color="#e1d6e9">
                         <frames>
                              <DOMFrame index="0" keyMode="9728">
                                   <elements>
                                        <DOMSymbolInstance libraryItemName="Symbol 149" centerPoint3DX="6.5" centerPoint3DY="-21.5">
                                             <matrix>
                                                  <Matrix tx="0.0" ty="-28.0"/>
                                             </matrix>
                                             <transformationPoint>
                                                  <Point/>
                                             </transformationPoint>
                                        </DOMSymbolInstance>
                                   </elements>
                              </DOMFrame>
                         </frames>
                    </DOMLayer>
                    <DOMLayer name="Layer 8" color="#bc19b0">
                         <frames>
                              <DOMFrame index="0" keyMode="9728">
                                   <elements>
                                        <DOMSymbolInstance libraryItemName="Symbol 149" centerPoint3DX="6.5" centerPoint3DY="-7.5">
                                             <matrix>
                                                  <Matrix tx="0.0" ty="-14.0"/>
                                             </matrix>
                                             <transformationPoint>
                                                  <Point/>
                                             </transformationPoint>
                                        </DOMSymbolInstance>
                                   </elements>
                              </DOMFrame>
                         </frames>
                    </DOMLayer>
                    <DOMLayer name="Layer 9" color="#e688dd" current="true" isSelected="true">
                         <frames>
                              <DOMFrame index="0" keyMode="9728">
                                   <elements>
                                        <DOMSymbolInstance libraryItemName="Symbol 149" centerPoint3DX="6.5" centerPoint3DY="6.5">
                                             <matrix>
                                                  <Matrix tx="0.0" ty="0.0"/>
                                             </matrix>
                                             <transformationPoint>
                                                  <Point/>
                                             </transformationPoint>
                                        </DOMSymbolInstance>
                                   </elements>
                              </DOMFrame>
                         </frames>
                    </DOMLayer>
               </layers>
          </DOMTimeline>
     </timeline>
</DOMSymbolItem>
