<DOMSymbolItem xmlns="http://ns.adobe.com/xfl/2008/" xmlns:xsi="http://www.w3.org/2001/XMLSchema-instance" name="Symbol 24" itemID="69d5d180-0000001c" lastModified="1775619668" symbolType="graphic">
     <timeline>
          <DOMTimeline name="Symbol 24" currentFrame="0">
               <layers>
                    <DOMLayer name="Layer 1">
                         <frames>
                              <DOMFrame index="0" motionTweenScale="false" keyMode="8192">
                                   <elements>
                                        <DOMShape isFloating="true">
                                             <fills>
                                                  <FillStyle index="1">
                                                       <SolidColor color="#ffffff" alpha="1.0"/>
                                                  </FillStyle>
                                                  <FillStyle index="2">
                                                       <SolidColor color="#000000" alpha="1.0"/>
                                                  </FillStyle>
                                             </fills>
                                             <strokes/>
                                             <edges>
                                                  <Edge fillStyle0="1" fillStyle1="2" strokeStyle="0" edges="! 336 879| 280 870[ 256 867 -600 865[ -652 864 -702 898| -725 930[ -791 1029 -805 1060| -869 1214| -905 1286| -926 1347| -950 1421[ -970 1564 -970 1638[ -970 1658 -955 1677[ -938 1697 -914 1698[ -836 1698 -794 1671| -792 1628[ -770 1545 -772 1512[ -777 1414 -770 1395[ -752 1342 -733 1315[ -724 1281 -705 1255[ -685 1226 -657 1201[ -603 1149 -558 1150[ -460 1149 -475 1303[ -475 1407 -510 1407[ -532 1407 -542 1391| -547 1373| -537 1302[ -537 1212 -560 1213[ -619 1213 -654 1289| -665 1314| -665 1316| -672 1336[ -680 1361 -680 1383[ -680 1440 -663 1478| -645 1492[ -611 1518 -543 1518[ -481 1518 -412 1492| -363 1473[ -372 1428 -372 1354| -367 1289[ -367 1247 -335 1225[ -269 1176 -243 1170| -140 1145[ -59 1145 -70 1230[ -74 1416 -135 1416[ -158 1416 -165 1401| -167 1384[ -132 1267 -132 1232[ -132 1203 -145 1203[ -169 1203 -228 1231[ -281 1254 -287 1261[ -305 1279 -305 1308| -310 1353[ -310 1436 -300 1470| -297 1479| -261 1512[ -217 1559 -184 1559[ -90 1559 -37 1516| -19 1503| -2 1481| 9 1470[ 11 1437 24 1402[ 43 1346 50 1298[ 52 1264 92 1211[ 148 1136 227 1136[ 337 1136 320 1259[ 306 1443 240 1444[ 220 1443 212 1430| 208 1415[ 258 1330 258 1261[ 258 1194 227 1195[ 181 1194 143 1257[ 118 1299 110 1334| 81 1418[ 70 1443 70 1483| 70 1484| 105 1502[ 154 1529 186 1529[ 306 1529 370 1445| 412 1309[ 438 1247 438 1170| 440 1144| 439 1074| 411 984[ 394 925 385 910| 336 879"/>
                                                  <Edge fillStyle0="0" fillStyle1="2" strokeStyle="0" edges="! 395 792| 410 800[ 443 819 465 845| 482 878| 483 879| 483 881| 510 956| 510 963[ 540 1046 540 1129| 539 1259[ 534 1309 510 1401[ 486 1459 437 1516[ 401 1559 362 1586[ 310 1648 242 1649[ 111 1649 54 1598| 50 1598[ 26 1597 -10 1630[ -47 1662 -160 1662[ -218 1662 -288 1621| -363 1578| -371 1578| -406 1606| -434 1613| -441 1617[ -501 1646 -630 1613[ -650 1619 -652 1653[ -655 1691 -689 1712| -721 1757[ -771 1801 -880 1801[ -1005 1801 -1050 1722[ -1064 1697 -1068 1666| -1070 1638[ -1070 1601 -1047 1415| -1015 1193[ -977 1035 -846 890[ -709 738 -610 766| -557 765[ -415 753 -65 753| 310 757| 330 762| 365 775| 395 792"/>
                                             </edges>
                                        </DOMShape>
                                   </elements>
                              </DOMFrame>
                         </frames>
                    </DOMLayer>
                    <DOMLayer name="Layer 2">
                         <frames>
                              <DOMFrame index="0" motionTweenScale="false" keyMode="8192">
                                   <elements>
                                        <DOMShape isFloating="true">
                                             <fills/>
                                             <strokes>
                                                  <StrokeStyle index="1">
                                                       <SolidStroke weight="10.0" scaleMode="normal">
                                                            <fill>
                                                                 <SolidColor color="#ffffff"/>
                                                            </fill>
                                                       </SolidStroke>
                                                  </StrokeStyle>
                                             </strokes>
                                             <edges>
                                                  <Edge fillStyle0="0" fillStyle1="0" strokeStyle="1" edges="! 330 762| 365 775| 395 792| 410 800[ 443 819 465 845| 482 878| 483 879| 483 881| 510 956| 510 963[ 540 1046 540 1129| 539 1259[ 534 1309 510 1401[ 486 1459 437 1516[ 401 1559 362 1586[ 310 1648 242 1649[ 111 1649 54 1598| 50 1598[ 26 1597 -10 1630[ -47 1662 -160 1662[ -218 1662 -288 1621| -363 1578| -371 1578| -406 1606| -434 1613| -441 1617[ -501 1646 -630 1613[ -650 1619 -652 1653[ -655 1691 -689 1712| -721 1757[ -771 1801 -880 1801[ -1005 1801 -1050 1722[ -1064 1697 -1068 1666| -1070 1638[ -1070 1601 -1047 1415| -1015 1193[ -977 1035 -846 890[ -709 738 -610 766| -557 765[ -415 753 -65 753| 310 757| 330 762"/>
                                             </edges>
                                        </DOMShape>
                                   </elements>
                              </DOMFrame>
                         </frames>
                    </DOMLayer>
               </layers>
          </DOMTimeline>
     </timeline>
</DOMSymbolItem>
